[{"buildOrder":77,"reportUrl":"https://Samuel-Leite.github.io/valentinos-magic-beans-ts-playwright/77/","reportName":"Allure Report with history","data":{}},{"buildOrder":79,"reportUrl":"https://Samuel-Leite.github.io/valentinos-magic-beans-ts-playwright/79/","reportName":"Allure Report with history","data":{}},{"buildOrder":76,"reportUrl":"https://Samuel-Leite.github.io/valentinos-magic-beans-ts-playwright/76/","reportName":"Allure Report with history","data":{}},{"buildOrder":75,"reportUrl":"https://Samuel-Leite.github.io/valentinos-magic-beans-ts-playwright/75/","reportName":"Allure Report with history","data":{}},{"buildOrder":74,"reportUrl":"https://Samuel-Leite.github.io/valentinos-magic-beans-ts-playwright/74/","reportName":"Allure Report with history","data":{}},{"buildOrder":73,"reportUrl":"https://Samuel-Leite.github.io/valentinos-magic-beans-ts-playwright/73/","reportName":"Allure Report with history","data":{}},{"buildOrder":72,"reportUrl":"https://Samuel-Leite.github.io/valentinos-magic-beans-ts-playwright/72/","reportName":"Allure Report with history","data":{}},{"buildOrder":71,"reportUrl":"https://Samuel-Leite.github.io/valentinos-magic-beans-ts-playwright/71/","reportName":"Allure Report with history","data":{}},{"buildOrder":70,"reportUrl":"https://Samuel-Leite.github.io/valentinos-magic-beans-ts-playwright/70/","reportName":"Allure Report with history","data":{}},{"buildOrder":69,"reportUrl":"https://Samuel-Leite.github.io/valentinos-magic-beans-ts-playwright/69/","reportName":"Allure Report with history","data":{}},{"buildOrder":68,"reportUrl":"https://Samuel-Leite.github.io/valentinos-magic-beans-ts-playwright/68/","reportName":"Allure Report with history","data":{}},{"buildOrder":67,"reportUrl":"https://Samuel-Leite.github.io/valentinos-magic-beans-ts-playwright/67/","reportName":"Allure Report with history","data":{}},{"buildOrder":66,"reportUrl":"https://Samuel-Leite.github.io/valentinos-magic-beans-ts-playwright/66/","reportName":"Allure Report with history","data":{}},{"buildOrder":65,"reportUrl":"https://Samuel-Leite.github.io/valentinos-magic-beans-ts-playwright/65/","reportName":"Allure Report with history","data":{}},{"buildOrder":64,"reportUrl":"https://Samuel-Leite.github.io/valentinos-magic-beans-ts-playwright/64/","reportName":"Allure Report with history","data":{}},{"buildOrder":63,"reportUrl":"https://Samuel-Leite.github.io/valentinos-magic-beans-ts-playwright/63/","reportName":"Allure Report with history","data":{}},{"buildOrder":62,"reportUrl":"https://Samuel-Leite.github.io/valentinos-magic-beans-ts-playwright/62/","reportName":"Allure Report with history","data":{}},{"buildOrder":60,"reportUrl":"https://Samuel-Leite.github.io/valentinos-magic-beans-ts-playwright/60/","reportName":"Allure Report with history","data":{}},{"buildOrder":61,"reportUrl":"https://Samuel-Leite.github.io/valentinos-magic-beans-ts-playwright/61/","reportName":"Allure Report with history","data":{}}]